TurtleBL/Ver.py
TurtleBL/__init__.py
turtleBL-0.0.32.dist-info/METADATA
turtleBL-0.0.32.dist-info/WHEEL
turtleBL-0.0.32.dist-info/top_level.txt
turtleBL-0.0.32.dist-info/RECORD
