Metadata-Version: 2.1
Name: turtleBL
Version: 0.0.32
Summary: A Python library for running small bots in the Roblox game Build Logic
Author: Back
License: GPL-3.0-or-later
Classifier: Programming Language :: Python :: 3
Classifier: License :: OSI Approved :: GNU General Public License v3 or later (GPLv3+)
Classifier: Operating System :: OS Independent
Requires-Python: >=3.6
